{"dependencies":[{"name":"C:\\Users\\Administrator\\Desktop\\my-svelteAPP\\node_modules\\webpack\\package.json","includedInParent":true,"mtime":1573714276584},{"name":"C:\\Users\\Administrator\\Desktop\\my-svelteAPP\\package.json","includedInParent":true,"mtime":1573809531295},{"name":"./ModuleDependency","loc":{"line":6,"column":33},"parent":"C:\\Users\\Administrator\\Desktop\\my-svelteAPP\\node_modules\\webpack\\lib\\dependencies\\SingleEntryDependency.js","resolved":"C:\\Users\\Administrator\\Desktop\\my-svelteAPP\\node_modules\\webpack\\lib\\dependencies\\ModuleDependency.js"}],"generated":{"js":"/*\n\tMIT License http://www.opensource.org/licenses/mit-license.php\n\tAuthor Tobias Koppers @sokra\n*/\n\"use strict\";\n\nvar ModuleDependency = require(\"./ModuleDependency\");\n\nclass SingleEntryDependency extends ModuleDependency {\n\t/**\n  * @param {string} request request path for entry\n  */\n\tconstructor(request) {\n\t\tsuper(request);\n\t}\n\n\tget type() {\n\t\treturn \"single entry\";\n\t}\n}\n\nmodule.exports = SingleEntryDependency;","map":{"mappings":[{"generated":{"line":1,"column":0},"source":"..\\node_modules\\webpack\\lib\\dependencies\\SingleEntryDependency.js","original":{"line":1,"column":0}},{"generated":{"line":5,"column":0},"source":"..\\node_modules\\webpack\\lib\\dependencies\\SingleEntryDependency.js","original":{"line":5,"column":0}},{"generated":{"line":7,"column":0},"source":"..\\node_modules\\webpack\\lib\\dependencies\\SingleEntryDependency.js","original":{"line":6,"column":0}},{"name":"ModuleDependency","generated":{"line":7,"column":4},"source":"..\\node_modules\\webpack\\lib\\dependencies\\SingleEntryDependency.js","original":{"line":6,"column":6}},{"name":"require","generated":{"line":7,"column":23},"source":"..\\node_modules\\webpack\\lib\\dependencies\\SingleEntryDependency.js","original":{"line":6,"column":25}},{"generated":{"line":7,"column":31},"source":"..\\node_modules\\webpack\\lib\\dependencies\\SingleEntryDependency.js","original":{"line":6,"column":33}},{"generated":{"line":7,"column":51},"source":"..\\node_modules\\webpack\\lib\\dependencies\\SingleEntryDependency.js","original":{"line":6,"column":25}},{"generated":{"line":7,"column":52},"source":"..\\node_modules\\webpack\\lib\\dependencies\\SingleEntryDependency.js","original":{"line":6,"column":0}},{"generated":{"line":9,"column":0},"source":"..\\node_modules\\webpack\\lib\\dependencies\\SingleEntryDependency.js","original":{"line":8,"column":0}},{"name":"SingleEntryDependency","generated":{"line":9,"column":6},"source":"..\\node_modules\\webpack\\lib\\dependencies\\SingleEntryDependency.js","original":{"line":8,"column":6}},{"generated":{"line":9,"column":27},"source":"..\\node_modules\\webpack\\lib\\dependencies\\SingleEntryDependency.js","original":{"line":8,"column":0}},{"name":"ModuleDependency","generated":{"line":9,"column":36},"source":"..\\node_modules\\webpack\\lib\\dependencies\\SingleEntryDependency.js","original":{"line":8,"column":36}},{"generated":{"line":9,"column":52},"source":"..\\node_modules\\webpack\\lib\\dependencies\\SingleEntryDependency.js","original":{"line":8,"column":0}},{"generated":{"line":9,"column":53},"source":"..\\node_modules\\webpack\\lib\\dependencies\\SingleEntryDependency.js","original":{"line":8,"column":53}},{"generated":{"line":10,"column":0},"source":"..\\node_modules\\webpack\\lib\\dependencies\\SingleEntryDependency.js","original":{"line":9,"column":1}},{"name":"constructor","generated":{"line":13,"column":0},"source":"..\\node_modules\\webpack\\lib\\dependencies\\SingleEntryDependency.js","original":{"line":12,"column":1}},{"name":"request","generated":{"line":13,"column":13},"source":"..\\node_modules\\webpack\\lib\\dependencies\\SingleEntryDependency.js","original":{"line":12,"column":13}},{"generated":{"line":13,"column":20},"source":"..\\node_modules\\webpack\\lib\\dependencies\\SingleEntryDependency.js","original":{"line":12,"column":1}},{"generated":{"line":13,"column":22},"source":"..\\node_modules\\webpack\\lib\\dependencies\\SingleEntryDependency.js","original":{"line":12,"column":22}},{"generated":{"line":14,"column":0},"source":"..\\node_modules\\webpack\\lib\\dependencies\\SingleEntryDependency.js","original":{"line":13,"column":2}},{"name":"request","generated":{"line":14,"column":8},"source":"..\\node_modules\\webpack\\lib\\dependencies\\SingleEntryDependency.js","original":{"line":13,"column":8}},{"generated":{"line":14,"column":15},"source":"..\\node_modules\\webpack\\lib\\dependencies\\SingleEntryDependency.js","original":{"line":13,"column":2}},{"generated":{"line":15,"column":0},"source":"..\\node_modules\\webpack\\lib\\dependencies\\SingleEntryDependency.js","original":{"line":14,"column":2}},{"generated":{"line":17,"column":0},"source":"..\\node_modules\\webpack\\lib\\dependencies\\SingleEntryDependency.js","original":{"line":16,"column":1}},{"name":"type","generated":{"line":17,"column":5},"source":"..\\node_modules\\webpack\\lib\\dependencies\\SingleEntryDependency.js","original":{"line":16,"column":5}},{"generated":{"line":17,"column":9},"source":"..\\node_modules\\webpack\\lib\\dependencies\\SingleEntryDependency.js","original":{"line":16,"column":1}},{"generated":{"line":17,"column":12},"source":"..\\node_modules\\webpack\\lib\\dependencies\\SingleEntryDependency.js","original":{"line":16,"column":12}},{"generated":{"line":18,"column":0},"source":"..\\node_modules\\webpack\\lib\\dependencies\\SingleEntryDependency.js","original":{"line":17,"column":2}},{"generated":{"line":18,"column":9},"source":"..\\node_modules\\webpack\\lib\\dependencies\\SingleEntryDependency.js","original":{"line":17,"column":9}},{"generated":{"line":18,"column":23},"source":"..\\node_modules\\webpack\\lib\\dependencies\\SingleEntryDependency.js","original":{"line":17,"column":2}},{"generated":{"line":19,"column":0},"source":"..\\node_modules\\webpack\\lib\\dependencies\\SingleEntryDependency.js","original":{"line":18,"column":2}},{"generated":{"line":20,"column":0},"source":"..\\node_modules\\webpack\\lib\\dependencies\\SingleEntryDependency.js","original":{"line":8,"column":53}},{"name":"module","generated":{"line":22,"column":0},"source":"..\\node_modules\\webpack\\lib\\dependencies\\SingleEntryDependency.js","original":{"line":21,"column":0}},{"name":"exports","generated":{"line":22,"column":7},"source":"..\\node_modules\\webpack\\lib\\dependencies\\SingleEntryDependency.js","original":{"line":21,"column":7}},{"generated":{"line":22,"column":14},"source":"..\\node_modules\\webpack\\lib\\dependencies\\SingleEntryDependency.js","original":{"line":21,"column":0}},{"name":"SingleEntryDependency","generated":{"line":22,"column":17},"source":"..\\node_modules\\webpack\\lib\\dependencies\\SingleEntryDependency.js","original":{"line":21,"column":17}},{"generated":{"line":22,"column":38},"source":"..\\node_modules\\webpack\\lib\\dependencies\\SingleEntryDependency.js","original":{"line":21,"column":0}}],"sources":{"..\\node_modules\\webpack\\lib\\dependencies\\SingleEntryDependency.js":"/*\n\tMIT License http://www.opensource.org/licenses/mit-license.php\n\tAuthor Tobias Koppers @sokra\n*/\n\"use strict\";\nconst ModuleDependency = require(\"./ModuleDependency\");\n\nclass SingleEntryDependency extends ModuleDependency {\n\t/**\n\t * @param {string} request request path for entry\n\t */\n\tconstructor(request) {\n\t\tsuper(request);\n\t}\n\n\tget type() {\n\t\treturn \"single entry\";\n\t}\n}\n\nmodule.exports = SingleEntryDependency;\n"},"lineCount":null}},"hash":"e173b94b87536b35e1f0eb937a104ff4","cacheData":{"env":{}},"id":299}